logmein_api_client-0.0.2.dist-info/DESCRIPTION.rst
logmein_api_client-0.0.2.dist-info/METADATA
logmein_api_client-0.0.2.dist-info/RECORD
logmein_api_client-0.0.2.dist-info/WHEEL
logmein_api_client-0.0.2.dist-info/metadata.json
logmein_api_client-0.0.2.dist-info/top_level.txt
logmeinapi/__init__.py
logmeinapi/client.py
logmeinapi/config.py
logmeinapi/exceptions.py
scriptlock/__init__.py
