Metadata-Version: 2.0
Name: logmein-api-client
Version: 0.0.2
Summary: Lock script to allow only one instance
Home-page: https://github.com/alkivi-sas/python-logmein-api-client
Author: Anthony Martinet
Author-email: anthony@alkivi.fr
License: LGPLv3
Keywords: logmein api rest
Platform: UNKNOWN
Classifier: Development Status :: 4 - Beta
Classifier: Environment :: Console
Classifier: Intended Audience :: Developers
Classifier: Topic :: Software Development :: Build Tools
Classifier: License :: OSI Approved :: GNU Lesser General Public License v3 (LGPLv3)
Classifier: Programming Language :: Python :: 2
Classifier: Programming Language :: Python :: 2.7
Classifier: Programming Language :: Python :: 3
Classifier: Programming Language :: Python :: 3.3
Classifier: Programming Language :: Python :: 3.4
Classifier: Programming Language :: Python :: 3.5
Requires-Dist: requests
Provides-Extra: dev
Provides-Extra: test
